coplin_db2-2.4.dist-info/licenses/LICENSE
db2/__init__.py
db2/__version__.py
db2/utils/__init__.py
coplin_db2-2.4.dist-info/METADATA
coplin_db2-2.4.dist-info/WHEEL
coplin_db2-2.4.dist-info/top_level.txt
coplin_db2-2.4.dist-info/RECORD
