Metadata-Version: 2.4
Name: coplin-db2
Version: 2.4
Summary: Um módulo de conveniência para manipulação de bancos de dados IBM DB2 em Python.
Home-page: https://github.com/COPLIN-UFSM/db2
Author: Henry Cagnini
Author-email: henry.cagnini@ufsm.br
License: MIT
Requires-Python: >=3.8,<3.12
License-File: LICENSE
Requires-Dist: numpy
Requires-Dist: pandas
Requires-Dist: ibm_db==3.1.4; platform_system == "Windows"
Requires-Dist: ibm_db; platform_system != "Windows"
Dynamic: author
Dynamic: author-email
Dynamic: description
Dynamic: description-content-type
Dynamic: home-page
Dynamic: license
Dynamic: license-file
Dynamic: requires-dist
Dynamic: requires-python
Dynamic: summary
